ACKS
COPYRIGHT
ChangeLog
MANIFEST.in
README
TODO
buildenv.in
configure
pct-speedtest.py
setup.py
Doc/epydoc-config
Doc/pycrypt.rst
LEGAL/00INDEX
LEGAL/CodeSubmissionRequirements.txt
LEGAL/tsu-notify.mbox
LEGAL/copy/00INDEX
LEGAL/copy/LICENSE.libtom
LEGAL/copy/LICENSE.orig
LEGAL/copy/LICENSE.python-2.2
LEGAL/copy/stmts/Andrew_M_Kuchling.mbox
LEGAL/copy/stmts/Barry_A_Warsaw.mbox
LEGAL/copy/stmts/Jeethu_Rao.mbox
LEGAL/copy/stmts/Joris_Bontje.mbox
LEGAL/copy/stmts/Mark_Moraes.mbox
LEGAL/copy/stmts/Paul_Swartz.mbox
LEGAL/copy/stmts/Robey_Pointer.asc
LEGAL/copy/stmts/Wim_Lewis.asc
build-aux/config.guess
build-aux/config.sub
build-aux/install-sh
build-aux/missing
dlitztest.egg-info/PKG-INFO
dlitztest.egg-info/SOURCES.txt
dlitztest.egg-info/dependency_links.txt
dlitztest.egg-info/top_level.txt
lib/Crypto/__init__.py
lib/Crypto/pct_warnings.py
lib/Crypto/Cipher/AES.py
lib/Crypto/Cipher/ARC2.py
lib/Crypto/Cipher/ARC4.py
lib/Crypto/Cipher/Blowfish.py
lib/Crypto/Cipher/CAST.py
lib/Crypto/Cipher/DES.py
lib/Crypto/Cipher/DES3.py
lib/Crypto/Cipher/PKCS1_OAEP.py
lib/Crypto/Cipher/PKCS1_v1_5.py
lib/Crypto/Cipher/XOR.py
lib/Crypto/Cipher/__init__.py
lib/Crypto/Cipher/blockalgo.py
lib/Crypto/Hash/HMAC.py
lib/Crypto/Hash/MD2.py
lib/Crypto/Hash/MD4.py
lib/Crypto/Hash/MD5.py
lib/Crypto/Hash/RIPEMD.py
lib/Crypto/Hash/RIPEMD160.py
lib/Crypto/Hash/SHA.py
lib/Crypto/Hash/SHA1.py
lib/Crypto/Hash/SHA224.py
lib/Crypto/Hash/SHA256.py
lib/Crypto/Hash/SHA384.py
lib/Crypto/Hash/SHA512.py
lib/Crypto/Hash/__init__.py
lib/Crypto/Hash/hashalgo.py
lib/Crypto/Protocol/AllOrNothing.py
lib/Crypto/Protocol/Chaffing.py
lib/Crypto/Protocol/KDF.py
lib/Crypto/Protocol/__init__.py
lib/Crypto/PublicKey/DSA.py
lib/Crypto/PublicKey/ElGamal.py
lib/Crypto/PublicKey/RSA.py
lib/Crypto/PublicKey/_DSA.py
lib/Crypto/PublicKey/_RSA.py
lib/Crypto/PublicKey/__init__.py
lib/Crypto/PublicKey/_slowmath.py
lib/Crypto/PublicKey/pubkey.py
lib/Crypto/Random/_UserFriendlyRNG.py
lib/Crypto/Random/__init__.py
lib/Crypto/Random/random.py
lib/Crypto/Random/Fortuna/FortunaAccumulator.py
lib/Crypto/Random/Fortuna/FortunaGenerator.py
