Metadata-Version: 1.1
Name: dlitztest
Version: 2.6
Summary: Don't use this package.
Home-page: UNKNOWN
Author: Dwayne C. Litzenberger
Author-email: dlitz@dlitz.net
License: UNKNOWN
Platform: UNKNOWN
Classifier: Development Status :: 5 - Production/Stable
Classifier: License :: Public Domain
Classifier: Intended Audience :: Developers
Classifier: Operating System :: Unix
Classifier: Operating System :: Microsoft :: Windows
Classifier: Operating System :: MacOS :: MacOS X
Classifier: Topic :: Security :: Cryptography
Classifier: Programming Language :: Python :: 2
Classifier: Programming Language :: Python :: 3
